nk_logger/__init__.py
nk_logger/log.py
nk_logger-1.0.0.dist-info/METADATA
nk_logger-1.0.0.dist-info/WHEEL
nk_logger-1.0.0.dist-info/top_level.txt
nk_logger-1.0.0.dist-info/RECORD
