Metadata-Version: 2.1
Name: nk-logger
Version: 1.0.0
Summary: A python logger that plays nice with datadog
Home-page: UNKNOWN
Author: UNKNOWN
Author-email: UNKNOWN
License: UNKNOWN
Platform: UNKNOWN
Requires-Dist: python-json-logger
